fuzztypes/__init__.py
fuzztypes/ascii.py
fuzztypes/const.py
fuzztypes/date.py
fuzztypes/emojis.py
fuzztypes/entity.py
fuzztypes/flags.py
fuzztypes/in_memory.py
fuzztypes/integer.py
fuzztypes/language.py
fuzztypes/lazy.py
fuzztypes/match.py
fuzztypes/on_disk.py
fuzztypes/person.py
fuzztypes/py.typed
fuzztypes/regex.py
fuzztypes/storage.py
fuzztypes/validation.py
fuzztypes/utils/__init__.py
fuzztypes/utils/download.py
fuzztypes-0.1.1.dist-info/METADATA
fuzztypes-0.1.1.dist-info/WHEEL
fuzztypes-0.1.1.dist-info/licenses/LICENSE
fuzztypes-0.1.1.dist-info/RECORD
