Metadata-Version: 2.3
Name: FuzzTypes
Version: 0.1.1
Summary: FuzzTypes is a Pydantic extension for annotating autocorrecting fields
Author-email: Ian Maurer <ian@genomoncology.com>
License-File: LICENSE
Classifier: Intended Audience :: Developers
Classifier: License :: OSI Approved :: MIT License
Classifier: Operating System :: OS Independent
Classifier: Programming Language :: Python :: 3
Classifier: Topic :: Software Development :: Libraries
Requires-Python: >=3.9
Requires-Dist: pydantic>=2.6.1
Provides-Extra: ext
Requires-Dist: anyascii; extra == 'ext'
Requires-Dist: dateparser; extra == 'ext'
Requires-Dist: emoji; extra == 'ext'
Requires-Dist: lancedb; extra == 'ext'
Requires-Dist: nameparser; extra == 'ext'
Requires-Dist: number-parser; extra == 'ext'
Requires-Dist: rapidfuzz; extra == 'ext'
Requires-Dist: sentence-transformers; extra == 'ext'
Requires-Dist: tantivy; extra == 'ext'
Requires-Dist: unidecode; extra == 'ext'
Provides-Extra: local
Requires-Dist: build; extra == 'local'
Requires-Dist: ipython; extra == 'local'
Requires-Dist: jupyter; extra == 'local'
Requires-Dist: mypy; extra == 'local'
Requires-Dist: pip; extra == 'local'
Requires-Dist: setuptools; extra == 'local'
Requires-Dist: twine; extra == 'local'
Provides-Extra: test
Requires-Dist: coverage[toml]; extra == 'test'
Requires-Dist: pytest; extra == 'test'
Requires-Dist: pytest-mock; extra == 'test'
